advlink/__init__.py
advlink/cls.py
advlink-0.2.0.dist-info/LICENCE
advlink-0.2.0.dist-info/METADATA
advlink-0.2.0.dist-info/WHEEL
advlink-0.2.0.dist-info/top_level.txt
advlink-0.2.0.dist-info/RECORD
