Metadata-Version: 2.1
Name: advlink
Version: 0.2.0
Summary: Useful link managment class
Home-page: https://github.com/mariohero24/advlink
Author: Guard Boi
Author-email: guard@cow.futbol
Classifier: Programming Language :: Python :: 3
Classifier: License :: OSI Approved :: MIT License
Classifier: Operating System :: OS Independent
License-File: LICENCE
